[{"id":2442,"caseType":"Accompaniment","caseTypeApiKey":"0659f77d-1658-e911-a971-eec0acf7c356","categoryId":2,"isArchived":false,"isActive":true,"caseSubTypes":[],"caseTypeId":null,"createdBy":null,"createdDate":null,"updateHistory":null,"countryCode":null},{"id":2204,"caseType":"Assessment","caseTypeApiKey":"2458f77d-1658-e911-a971-eec0acf7c356","categoryId":24,"isArchived":false,"isActive":true,"caseSubTypes":[],"caseTypeId":null,"createdBy":null,"createdDate":null,"updateHistory":null,"countryCode":null},{"id":3987,"caseType":"Assessment","caseTypeApiKey":"06f31c7f-1658-e911-a971-eec0acf7c356","categoryId":2,"isArchived":false,"isActive":true,"caseSubTypes":[],"caseTypeId":null,"createdBy":null,"createdDate":null,"updateHistory":null,"countryCode":null},{"id":2135,"caseType":"Business Visa","caseTypeApiKey":"e257f77d-1658-e911-a971-eec0acf7c356","categoryId":1,"isArchived":false,"isActive":true,"caseSubTypes":[],"caseTypeId":null,"createdBy":null,"createdDate":null,"updateHistory":null,"countryCode":null},{"id":2205,"caseType":"Cancellation Fee","caseTypeApiKey":"2558f77d-1658-e911-a971-eec0acf7c356","categoryId":24,"isArchived":false,"isActive":true,"caseSubTypes":[],"caseTypeId":null,"createdBy":null,"createdDate":null,"updateHistory":null,"countryCode":null},{"id":2443,"caseType":"Change of Address","caseTypeApiKey":"0759f77d-1658-e911-a971-eec0acf7c356","categoryId":2,"isArchived":false,"isActive":true,"caseSubTypes":[],"caseTypeId":null,"createdBy":null,"createdDate":null,"updateHistory":null,"countryCode":null},{"id":2444,"caseType":"Change of Passport","caseTypeApiKey":"0859f77d-1658-e911-a971-eec0acf7c356","categoryId":2,"isArchived":false,"isActive":true,"caseSubTypes":[],"caseTypeId":null,"createdBy":null,"createdDate":null,"updateHistory":null,"countryCode":null},{"id":2206,"caseType":"Company License","caseTypeApiKey":"2658f77d-1658-e911-a971-eec0acf7c356","categoryId":24,"isArchived":false,"isActive":true,"caseSubTypes":[],"caseTypeId":null,"createdBy":null,"createdDate":null,"updateHistory":null,"countryCode":null},{"id":2207,"caseType":"Company Registration","caseTypeApiKey":"2758f77d-1658-e911-a971-eec0acf7c356","categoryId":24,"isArchived":false,"isActive":true,"caseSubTypes":[],"caseTypeId":null,"createdBy":null,"createdDate":null,"updateHistory":null,"countryCode":null},{"id":2166,"caseType":"Consultation","caseTypeApiKey":"0158f77d-1658-e911-a971-eec0acf7c356","categoryId":26,"isArchived":false,"isActive":true,"caseSubTypes":[],"caseTypeId":null,"createdBy":null,"createdDate":null,"updateHistory":null,"countryCode":null},{"id":2313,"caseType":"Document Legalization","caseTypeApiKey":"8f58f77d-1658-e911-a971-eec0acf7c356","categoryId":23,"isArchived":false,"isActive":true,"caseSubTypes":[],"caseTypeId":null,"createdBy":null,"createdDate":null,"updateHistory":null,"countryCode":null},{"id":9802,"caseType":"Document Procurement/Acquisition","caseTypeApiKey":"bd091d7f-1658-e911-a971-eec0acf7c356","categoryId":23,"isArchived":null,"isActive":true,"caseSubTypes":[],"caseTypeId":null,"createdBy":null,"createdDate":null,"updateHistory":null,"countryCode":null},{"id":10235,"caseType":"Emergency Work Permit","caseTypeApiKey":"6e0b1d7f-1658-e911-a971-eec0acf7c356","categoryId":4,"isArchived":null,"isActive":true,"caseSubTypes":[],"caseTypeId":null,"createdBy":null,"createdDate":null,"updateHistory":null,"countryCode":null},{"id":10185,"caseType":"Limited Stay Visa","caseTypeApiKey":"3c0b1d7f-1658-e911-a971-eec0acf7c356","categoryId":1,"isArchived":null,"isActive":true,"caseSubTypes":[],"caseTypeId":null,"createdBy":null,"createdDate":null,"updateHistory":null,"countryCode":null},{"id":4521,"caseType":"Miscellaneous","caseTypeApiKey":"1cf51c7f-1658-e911-a971-eec0acf7c356","categoryId":2,"isArchived":false,"isActive":true,"caseSubTypes":[],"caseTypeId":null,"createdBy":null,"createdDate":null,"updateHistory":null,"countryCode":null},{"id":2446,"caseType":"Multiple Entry Business Visa","caseTypeApiKey":"0959f77d-1658-e911-a971-eec0acf7c356","categoryId":2,"isArchived":false,"isActive":true,"caseSubTypes":[],"caseTypeId":null,"createdBy":null,"createdDate":null,"updateHistory":null,"countryCode":null},{"id":2314,"caseType":"Police Clearance","caseTypeApiKey":"9058f77d-1658-e911-a971-eec0acf7c356","categoryId":23,"isArchived":false,"isActive":true,"caseSubTypes":[],"caseTypeId":null,"createdBy":null,"createdDate":null,"updateHistory":null,"countryCode":null},{"id":2550,"caseType":"Residence Permit","caseTypeApiKey":"6ced1c7f-1658-e911-a971-eec0acf7c356","categoryId":3,"isArchived":false,"isActive":true,"caseSubTypes":[],"caseTypeId":null,"createdBy":null,"createdDate":null,"updateHistory":null,"countryCode":null},{"id":2136,"caseType":"Telex Visa (VITAS)","caseTypeApiKey":"e357f77d-1658-e911-a971-eec0acf7c356","categoryId":1,"isArchived":false,"isActive":true,"caseSubTypes":[],"caseTypeId":null,"createdBy":null,"createdDate":null,"updateHistory":null,"countryCode":null},{"id":2137,"caseType":"Tourist Visa","caseTypeApiKey":"e457f77d-1658-e911-a971-eec0acf7c356","categoryId":1,"isArchived":false,"isActive":true,"caseSubTypes":[],"caseTypeId":null,"createdBy":null,"createdDate":null,"updateHistory":null,"countryCode":null},{"id":3499,"caseType":"Tracking","caseTypeApiKey":"1ef11c7f-1658-e911-a971-eec0acf7c356","categoryId":2,"isArchived":false,"isActive":true,"caseSubTypes":[],"caseTypeId":null,"createdBy":null,"createdDate":null,"updateHistory":null,"countryCode":null},{"id":2315,"caseType":"Translation Arrangement","caseTypeApiKey":"9158f77d-1658-e911-a971-eec0acf7c356","categoryId":23,"isArchived":false,"isActive":true,"caseSubTypes":[],"caseTypeId":null,"createdBy":null,"createdDate":null,"updateHistory":null,"countryCode":null},{"id":2208,"caseType":"Travel Assessment","caseTypeApiKey":"2858f77d-1658-e911-a971-eec0acf7c356","categoryId":24,"isArchived":false,"isActive":true,"caseSubTypes":[],"caseTypeId":null,"createdBy":null,"createdDate":null,"updateHistory":null,"countryCode":null},{"id":3744,"caseType":"Travel Assessment","caseTypeApiKey":"13f21c7f-1658-e911-a971-eec0acf7c356","categoryId":2,"isArchived":false,"isActive":true,"caseSubTypes":[],"caseTypeId":null,"createdBy":null,"createdDate":null,"updateHistory":null,"countryCode":null},{"id":2447,"caseType":"Visa on Arrival Extension","caseTypeApiKey":"0a59f77d-1658-e911-a971-eec0acf7c356","categoryId":2,"isArchived":false,"isActive":true,"caseSubTypes":[],"caseTypeId":null,"createdBy":null,"createdDate":null,"updateHistory":null,"countryCode":null},{"id":2642,"caseType":"Work Permit","caseTypeApiKey":"c8ed1c7f-1658-e911-a971-eec0acf7c356","categoryId":4,"isArchived":false,"isActive":true,"caseSubTypes":[],"caseTypeId":null,"createdBy":null,"createdDate":null,"updateHistory":null,"countryCode":null}]