[{"id":10242,"caseType":"14 Day Work Permission","caseTypeApiKey":"750b1d7f-1658-e911-a971-eec0acf7c356","categoryId":4,"isArchived":null,"isActive":true,"caseSubTypes":[],"caseTypeId":null,"createdBy":null,"createdDate":null,"updateHistory":null,"countryCode":null},{"id":2448,"caseType":"Application for Recognition of de facto Relationship","caseTypeApiKey":"0b59f77d-1658-e911-a971-eec0acf7c356","categoryId":2,"isArchived":false,"isActive":true,"caseSubTypes":[],"caseTypeId":null,"createdBy":null,"createdDate":null,"updateHistory":null,"countryCode":null},{"id":2450,"caseType":"Assessment","caseTypeApiKey":"0d59f77d-1658-e911-a971-eec0acf7c356","categoryId":2,"isArchived":false,"isActive":true,"caseSubTypes":[],"caseTypeId":null,"createdBy":null,"createdDate":null,"updateHistory":null,"countryCode":null},{"id":2643,"caseType":"Atypical Working Scheme","caseTypeApiKey":"c9ed1c7f-1658-e911-a971-eec0acf7c356","categoryId":4,"isArchived":false,"isActive":true,"caseSubTypes":[],"caseTypeId":null,"createdBy":null,"createdDate":null,"updateHistory":null,"countryCode":null},{"id":2451,"caseType":"Change of Role","caseTypeApiKey":"0e59f77d-1658-e911-a971-eec0acf7c356","categoryId":2,"isArchived":false,"isActive":true,"caseSubTypes":[],"caseTypeId":null,"createdBy":null,"createdDate":null,"updateHistory":null,"countryCode":null},{"id":2167,"caseType":"Consultation","caseTypeApiKey":"0258f77d-1658-e911-a971-eec0acf7c356","categoryId":26,"isArchived":false,"isActive":true,"caseSubTypes":[],"caseTypeId":null,"createdBy":null,"createdDate":null,"updateHistory":null,"countryCode":null},{"id":2644,"caseType":"Contract for Services Employment Permit","caseTypeApiKey":"caed1c7f-1658-e911-a971-eec0acf7c356","categoryId":4,"isArchived":false,"isActive":true,"caseSubTypes":[],"caseTypeId":null,"createdBy":null,"createdDate":null,"updateHistory":null,"countryCode":null},{"id":2645,"caseType":"Critical Skills Employment Permit","caseTypeApiKey":"cbed1c7f-1658-e911-a971-eec0acf7c356","categoryId":4,"isArchived":false,"isActive":true,"caseSubTypes":[],"caseTypeId":null,"createdBy":null,"createdDate":null,"updateHistory":null,"countryCode":null},{"id":10601,"caseType":"DBEI Notification","caseTypeApiKey":"b6da85d7-6c36-eb11-a98a-b39a22e7dbcf","categoryId":2,"isArchived":null,"isActive":true,"caseSubTypes":[],"caseTypeId":null,"createdBy":null,"createdDate":null,"updateHistory":null,"countryCode":null},{"id":10651,"caseType":"Dependent of UK Family Member","caseTypeApiKey":"f5113e8e-da5c-eb11-a98b-8bb20352a86b","categoryId":2,"isArchived":null,"isActive":true,"caseSubTypes":[],"caseTypeId":null,"createdBy":null,"createdDate":null,"updateHistory":null,"countryCode":null},{"id":9765,"caseType":"Document Legalization","caseTypeApiKey":"98091d7f-1658-e911-a971-eec0acf7c356","categoryId":23,"isArchived":null,"isActive":true,"caseSubTypes":[],"caseTypeId":null,"createdBy":null,"createdDate":null,"updateHistory":null,"countryCode":null},{"id":2316,"caseType":"Document Procurement/Acquisition","caseTypeApiKey":"9258f77d-1658-e911-a971-eec0acf7c356","categoryId":23,"isArchived":false,"isActive":true,"caseSubTypes":[],"caseTypeId":null,"createdBy":null,"createdDate":null,"updateHistory":null,"countryCode":null},{"id":2138,"caseType":"Entry Visa","caseTypeApiKey":"e557f77d-1658-e911-a971-eec0acf7c356","categoryId":1,"isArchived":false,"isActive":true,"caseSubTypes":[],"caseTypeId":null,"createdBy":null,"createdDate":null,"updateHistory":null,"countryCode":null},{"id":2452,"caseType":"Foreign Birth Registration (FBR)","caseTypeApiKey":"0f59f77d-1658-e911-a971-eec0acf7c356","categoryId":2,"isArchived":false,"isActive":true,"caseSubTypes":[],"caseTypeId":null,"createdBy":null,"createdDate":null,"updateHistory":null,"countryCode":null},{"id":10315,"caseType":"Foreign Birth Registration (FBR)","caseTypeApiKey":"be0b1d7f-1658-e911-a971-eec0acf7c356","categoryId":25,"isArchived":null,"isActive":true,"caseSubTypes":[],"caseTypeId":null,"createdBy":null,"createdDate":null,"updateHistory":null,"countryCode":null},{"id":10317,"caseType":"Formal Notification of Role","caseTypeApiKey":"c00b1d7f-1658-e911-a971-eec0acf7c356","categoryId":2,"isArchived":null,"isActive":true,"caseSubTypes":[],"caseTypeId":null,"createdBy":null,"createdDate":null,"updateHistory":null,"countryCode":null},{"id":2646,"caseType":"General Employment Permit","caseTypeApiKey":"cced1c7f-1658-e911-a971-eec0acf7c356","categoryId":4,"isArchived":false,"isActive":true,"caseSubTypes":[],"caseTypeId":null,"createdBy":null,"createdDate":null,"updateHistory":null,"countryCode":null},{"id":2647,"caseType":"Internship Employment Permit","caseTypeApiKey":"cded1c7f-1658-e911-a971-eec0acf7c356","categoryId":4,"isArchived":false,"isActive":true,"caseSubTypes":[],"caseTypeId":null,"createdBy":null,"createdDate":null,"updateHistory":null,"countryCode":null},{"id":2648,"caseType":"Intra-Company Transfer Employment Permit","caseTypeApiKey":"ceed1c7f-1658-e911-a971-eec0acf7c356","categoryId":4,"isArchived":false,"isActive":true,"caseSubTypes":[],"caseTypeId":null,"createdBy":null,"createdDate":null,"updateHistory":null,"countryCode":null},{"id":2317,"caseType":"Legalizations","caseTypeApiKey":"9358f77d-1658-e911-a971-eec0acf7c356","categoryId":23,"isArchived":false,"isActive":true,"caseSubTypes":[],"caseTypeId":null,"createdBy":null,"createdDate":null,"updateHistory":null,"countryCode":null},{"id":2318,"caseType":"Letter of Invitation","caseTypeApiKey":"9458f77d-1658-e911-a971-eec0acf7c356","categoryId":23,"isArchived":false,"isActive":true,"caseSubTypes":[],"caseTypeId":null,"createdBy":null,"createdDate":null,"updateHistory":null,"countryCode":null},{"id":2319,"caseType":"Letter of Support","caseTypeApiKey":"9558f77d-1658-e911-a971-eec0acf7c356","categoryId":23,"isArchived":false,"isActive":true,"caseSubTypes":[],"caseTypeId":null,"createdBy":null,"createdDate":null,"updateHistory":null,"countryCode":null},{"id":4522,"caseType":"Miscellaneous","caseTypeApiKey":"1df51c7f-1658-e911-a971-eec0acf7c356","categoryId":2,"isArchived":false,"isActive":true,"caseSubTypes":[],"caseTypeId":null,"createdBy":null,"createdDate":null,"updateHistory":null,"countryCode":null},{"id":10275,"caseType":"Mock Audit","caseTypeApiKey":"960b1d7f-1658-e911-a971-eec0acf7c356","categoryId":24,"isArchived":null,"isActive":true,"caseSubTypes":[],"caseTypeId":null,"createdBy":null,"createdDate":null,"updateHistory":null,"countryCode":null},{"id":10254,"caseType":"Multiple Re-entry Visa","caseTypeApiKey":"810b1d7f-1658-e911-a971-eec0acf7c356","categoryId":3,"isArchived":null,"isActive":true,"caseSubTypes":[],"caseTypeId":null,"createdBy":null,"createdDate":null,"updateHistory":null,"countryCode":null},{"id":2085,"caseType":"Naturalization","caseTypeApiKey":"b057f77d-1658-e911-a971-eec0acf7c356","categoryId":25,"isArchived":false,"isActive":true,"caseSubTypes":[],"caseTypeId":null,"createdBy":null,"createdDate":null,"updateHistory":null,"countryCode":null},{"id":10316,"caseType":"Passport","caseTypeApiKey":"bf0b1d7f-1658-e911-a971-eec0acf7c356","categoryId":25,"isArchived":null,"isActive":true,"caseSubTypes":[],"caseTypeId":null,"createdBy":null,"createdDate":null,"updateHistory":null,"countryCode":null},{"id":2455,"caseType":"Posted Worker Notification","caseTypeApiKey":"1159f77d-1658-e911-a971-eec0acf7c356","categoryId":2,"isArchived":false,"isActive":true,"caseSubTypes":[],"caseTypeId":null,"createdBy":null,"createdDate":null,"updateHistory":null,"countryCode":null},{"id":10320,"caseType":"Re-Entry Visa","caseTypeApiKey":"c30b1d7f-1658-e911-a971-eec0acf7c356","categoryId":1,"isArchived":null,"isActive":true,"caseSubTypes":[],"caseTypeId":null,"createdBy":null,"createdDate":null,"updateHistory":null,"countryCode":null},{"id":2456,"caseType":"Replacement GNIB Card","caseTypeApiKey":"1259f77d-1658-e911-a971-eec0acf7c356","categoryId":2,"isArchived":false,"isActive":true,"caseSubTypes":[],"caseTypeId":null,"createdBy":null,"createdDate":null,"updateHistory":null,"countryCode":null},{"id":2551,"caseType":"Residence Permit for Dependent","caseTypeApiKey":"6ded1c7f-1658-e911-a971-eec0acf7c356","categoryId":3,"isArchived":false,"isActive":true,"caseSubTypes":[],"caseTypeId":null,"createdBy":null,"createdDate":null,"updateHistory":null,"countryCode":null},{"id":2552,"caseType":"Residence Permit for Employment","caseTypeApiKey":"6eed1c7f-1658-e911-a971-eec0acf7c356","categoryId":3,"isArchived":false,"isActive":true,"caseSubTypes":[],"caseTypeId":null,"createdBy":null,"createdDate":null,"updateHistory":null,"countryCode":null},{"id":2139,"caseType":"Short Stay C Visa","caseTypeApiKey":"e657f77d-1658-e911-a971-eec0acf7c356","categoryId":1,"isArchived":false,"isActive":true,"caseSubTypes":[],"caseTypeId":null,"createdBy":null,"createdDate":null,"updateHistory":null,"countryCode":null},{"id":2457,"caseType":"Spousal/Partner Employment Pass","caseTypeApiKey":"1359f77d-1658-e911-a971-eec0acf7c356","categoryId":2,"isArchived":false,"isActive":true,"caseSubTypes":[],"caseTypeId":null,"createdBy":null,"createdDate":null,"updateHistory":null,"countryCode":null},{"id":10318,"caseType":"Stamp 0","caseTypeApiKey":"c10b1d7f-1658-e911-a971-eec0acf7c356","categoryId":3,"isArchived":null,"isActive":true,"caseSubTypes":[],"caseTypeId":null,"createdBy":null,"createdDate":null,"updateHistory":null,"countryCode":null},{"id":10534,"caseType":"Stamp 1","caseTypeApiKey":"08183523-2295-ea11-a980-54e63354f201","categoryId":3,"isArchived":null,"isActive":true,"caseSubTypes":[],"caseTypeId":null,"createdBy":null,"createdDate":null,"updateHistory":null,"countryCode":null},{"id":10535,"caseType":"Stamp 1G","caseTypeApiKey":"8c80202a-2295-ea11-a980-54e63354f201","categoryId":3,"isArchived":null,"isActive":true,"caseSubTypes":[],"caseTypeId":null,"createdBy":null,"createdDate":null,"updateHistory":null,"countryCode":null},{"id":2458,"caseType":"Stamp 3","caseTypeApiKey":"1459f77d-1658-e911-a971-eec0acf7c356","categoryId":3,"isArchived":false,"isActive":true,"caseSubTypes":[],"caseTypeId":null,"createdBy":null,"createdDate":null,"updateHistory":null,"countryCode":null},{"id":10598,"caseType":"Stamp 3 - EU Treaty Rights","caseTypeApiKey":"d92ce0a4-852a-eb11-a987-54e63354f201","categoryId":2,"isArchived":null,"isActive":true,"caseSubTypes":[],"caseTypeId":null,"createdBy":null,"createdDate":null,"updateHistory":null,"countryCode":null},{"id":2459,"caseType":"Stamp 4","caseTypeApiKey":"1559f77d-1658-e911-a971-eec0acf7c356","categoryId":2,"isArchived":false,"isActive":true,"caseSubTypes":[],"caseTypeId":null,"createdBy":null,"createdDate":null,"updateHistory":null,"countryCode":null},{"id":10321,"caseType":"Stamp 4","caseTypeApiKey":"c40b1d7f-1658-e911-a971-eec0acf7c356","categoryId":4,"isArchived":null,"isActive":true,"caseSubTypes":[],"caseTypeId":null,"createdBy":null,"createdDate":null,"updateHistory":null,"countryCode":null},{"id":10319,"caseType":"Stamp 4 - EU Treaty Rights","caseTypeApiKey":"c20b1d7f-1658-e911-a971-eec0acf7c356","categoryId":2,"isArchived":null,"isActive":true,"caseSubTypes":[],"caseTypeId":null,"createdBy":null,"createdDate":null,"updateHistory":null,"countryCode":null},{"id":10322,"caseType":"Stamp 4 Support Letter","caseTypeApiKey":"c50b1d7f-1658-e911-a971-eec0acf7c356","categoryId":4,"isArchived":null,"isActive":true,"caseSubTypes":[],"caseTypeId":null,"createdBy":null,"createdDate":null,"updateHistory":null,"countryCode":null},{"id":2460,"caseType":"Stamp 5","caseTypeApiKey":"1659f77d-1658-e911-a971-eec0acf7c356","categoryId":2,"isArchived":false,"isActive":true,"caseSubTypes":[],"caseTypeId":null,"createdBy":null,"createdDate":null,"updateHistory":null,"countryCode":null},{"id":10599,"caseType":"Stamp 5 - EU Treaty Rights","caseTypeApiKey":"789826c6-852a-eb11-a987-54e63354f201","categoryId":2,"isArchived":null,"isActive":true,"caseSubTypes":[],"caseTypeId":null,"createdBy":null,"createdDate":null,"updateHistory":null,"countryCode":null},{"id":2461,"caseType":"Statement of Loss","caseTypeApiKey":"1759f77d-1658-e911-a971-eec0acf7c356","categoryId":2,"isArchived":false,"isActive":true,"caseSubTypes":[],"caseTypeId":null,"createdBy":null,"createdDate":null,"updateHistory":null,"countryCode":null},{"id":3500,"caseType":"Tracking","caseTypeApiKey":"1ff11c7f-1658-e911-a971-eec0acf7c356","categoryId":2,"isArchived":false,"isActive":true,"caseSubTypes":[],"caseTypeId":null,"createdBy":null,"createdDate":null,"updateHistory":null,"countryCode":null},{"id":2209,"caseType":"Transfer of Undertaking","caseTypeApiKey":"2958f77d-1658-e911-a971-eec0acf7c356","categoryId":24,"isArchived":false,"isActive":true,"caseSubTypes":[],"caseTypeId":null,"createdBy":null,"createdDate":null,"updateHistory":null,"countryCode":null},{"id":2322,"caseType":"Translations","caseTypeApiKey":"9858f77d-1658-e911-a971-eec0acf7c356","categoryId":23,"isArchived":false,"isActive":true,"caseSubTypes":[],"caseTypeId":null,"createdBy":null,"createdDate":null,"updateHistory":null,"countryCode":null},{"id":2453,"caseType":"Travel Assessment","caseTypeApiKey":"1059f77d-1658-e911-a971-eec0acf7c356","categoryId":2,"isArchived":false,"isActive":true,"caseSubTypes":[],"caseTypeId":null,"createdBy":null,"createdDate":null,"updateHistory":null,"countryCode":null},{"id":2210,"caseType":"Trusted Partner Registration","caseTypeApiKey":"2a58f77d-1658-e911-a971-eec0acf7c356","categoryId":24,"isArchived":false,"isActive":true,"caseSubTypes":[],"caseTypeId":null,"createdBy":null,"createdDate":null,"updateHistory":null,"countryCode":null}]