[{"id":3942,"caseType":"Assessment","caseTypeApiKey":"d9f21c7f-1658-e911-a971-eec0acf7c356","categoryId":2,"isArchived":false,"isActive":true,"caseSubTypes":[],"caseTypeId":null,"createdBy":null,"createdDate":null,"updateHistory":null,"countryCode":null},{"id":4182,"caseType":"Consultation","caseTypeApiKey":"c9f31c7f-1658-e911-a971-eec0acf7c356","categoryId":26,"isArchived":false,"isActive":true,"caseSubTypes":[],"caseTypeId":null,"createdBy":null,"createdDate":null,"updateHistory":null,"countryCode":null},{"id":9754,"caseType":"Document Legalization","caseTypeApiKey":"8d091d7f-1658-e911-a971-eec0acf7c356","categoryId":23,"isArchived":null,"isActive":true,"caseSubTypes":[],"caseTypeId":null,"createdBy":null,"createdDate":null,"updateHistory":null,"countryCode":null},{"id":9757,"caseType":"Document Procurement/Acquisition","caseTypeApiKey":"90091d7f-1658-e911-a971-eec0acf7c356","categoryId":23,"isArchived":null,"isActive":true,"caseSubTypes":[],"caseTypeId":null,"createdBy":null,"createdDate":null,"updateHistory":null,"countryCode":null},{"id":4473,"caseType":"Miscellaneous","caseTypeApiKey":"ecf41c7f-1658-e911-a971-eec0acf7c356","categoryId":2,"isArchived":false,"isActive":true,"caseSubTypes":[],"caseTypeId":null,"createdBy":null,"createdDate":null,"updateHistory":null,"countryCode":null},{"id":3451,"caseType":"Tracking","caseTypeApiKey":"eef01c7f-1658-e911-a971-eec0acf7c356","categoryId":2,"isArchived":false,"isActive":true,"caseSubTypes":[],"caseTypeId":null,"createdBy":null,"createdDate":null,"updateHistory":null,"countryCode":null},{"id":3699,"caseType":"Travel Assessment","caseTypeApiKey":"e6f11c7f-1658-e911-a971-eec0acf7c356","categoryId":2,"isArchived":false,"isActive":true,"caseSubTypes":[],"caseTypeId":null,"createdBy":null,"createdDate":null,"updateHistory":null,"countryCode":null}]